namecheap/__init__.py
namecheap/exceptions.py
namecheap/helpers.py
namecheap/namecheap.py
namecheap/objects.py
privex_namecheap-0.1.2.data/scripts/namecheap-api-cli
privex_namecheap-0.1.2.dist-info/LICENSE.txt
privex_namecheap-0.1.2.dist-info/METADATA
privex_namecheap-0.1.2.dist-info/WHEEL
privex_namecheap-0.1.2.dist-info/top_level.txt
privex_namecheap-0.1.2.dist-info/RECORD
