Metadata-Version: 2.1
Name: privex-namecheap
Version: 0.1.2
Summary: Namecheap API client in Python (fork of Bemmu/PyNamecheap)
Home-page: https://github.com/Privex/PyNamecheap
Author: Privex Inc.
Author-email: company@privex.io
License: MIT
Platform: any
Classifier: Environment :: Web Environment
Classifier: Intended Audience :: Developers
Classifier: Programming Language :: Python :: 3
Classifier: Programming Language :: Python :: 3.6
Classifier: Programming Language :: Python :: 3.7
Classifier: Programming Language :: Python :: 3.8
Classifier: License :: OSI Approved :: MIT License
Classifier: Operating System :: OS Independent
Classifier: Topic :: Internet :: WWW/HTTP
Classifier: Topic :: Software Development :: Libraries :: Python Modules
Requires-Dist: requests
Requires-Dist: privex-helpers (>=2.18.0)
Requires-Dist: privex-loghelper
Provides-Extra: dataclasses
Requires-Dist: dataclasses (>=0.7) ; extra == 'dataclasses'
Provides-Extra: dev
Requires-Dist: setuptools ; extra == 'dev'
Requires-Dist: wheel ; extra == 'dev'
Requires-Dist: twine ; extra == 'dev'
Requires-Dist: nose ; extra == 'dev'
Requires-Dist: privex-helpers[setuppy] ; extra == 'dev'
Provides-Extra: py36
Requires-Dist: dataclasses (>=0.7) ; extra == 'py36'
